rankmyapp_logger/__init__.py
rankmyapp_logger/logger.py
rankmyapp_logger/contracts/__init__.py
rankmyapp_logger/contracts/enums.py
rankmyapp_logger/contracts/message.py
rankmyapp_logger/contracts/transport.py
rankmyapp_logger/services/__init__.py
rankmyapp_logger/services/http_service.py
rankmyapp_logger/services/http_service_test.py
rankmyapp_logger/transports/__init__.py
rankmyapp_logger/transports/amqp_transport.py
rankmyapp_logger/transports/amqp_transport_test.py
rankmyapp_logger/transports/http_transport.py
rankmyapp_logger/transports/http_transport_test.py
rankmyapp_logger-0.0.7.dist-info/METADATA
rankmyapp_logger-0.0.7.dist-info/WHEEL
rankmyapp_logger-0.0.7.dist-info/top_level.txt
rankmyapp_logger-0.0.7.dist-info/RECORD
