Metadata-Version: 2.2
Name: rankmyapp_logger
Version: 0.0.7
Summary: A internal logger library
Author: rankmyapp
Classifier: Programming Language :: Python :: 3
Classifier: License :: OSI Approved :: MIT License
Classifier: Operating System :: OS Independent
Requires-Python: >=3.8
Requires-Dist: requests==2.32.3
Requires-Dist: pika==1.3.2
Dynamic: author
Dynamic: classifier
Dynamic: description
Dynamic: description-content-type
Dynamic: requires-dist
Dynamic: requires-python
Dynamic: summary
